sphinx_godot/__init__.py
sphinx_godot/descriptions.py
sphinx_godot/gdscript.py
sphinx_godot/theme.toml
sphinx_godot/static/favicon.ico
sphinx_godot/static/godot/css/main.css
sphinx_godot/static/godot/css/fonts/JetBrainsMono-Bold.woff2
sphinx_godot/static/godot/css/fonts/JetBrainsMono-Medium.woff2
sphinx_godot/static/godot/css/fonts/JetBrainsMono-Regular.woff2
sphinx_godot/static/godot/css/fonts/Montserrat-Bold.woff2
sphinx_godot/static/godot/img/docs_logo.svg
sphinx_godot/static/godot/js/main.js
sphinx_godot/templates/breadcrumbs.html
sphinx_godot/templates/footer.html
sphinx_godot/templates/layout.html
sphinx_godot/templates/versions.html
sphinx_godot-0.0.7.dist-info/entry_points.txt
sphinx_godot-0.0.7.dist-info/LICENSE.md
sphinx_godot-0.0.7.dist-info/WHEEL
sphinx_godot-0.0.7.dist-info/METADATA
sphinx_godot-0.0.7.dist-info/RECORD
