Metadata-Version: 2.3
Name: sphinx_godot
Version: 0.0.7
Summary: A Sphinx theme based on the official Godot documentation.
Author-email: opsocket <opsocket@pm.me>
Requires-Python: >=3.8
Classifier: Programming Language :: Python :: 3
Classifier: License :: OSI Approved :: GNU General Public License v3 or later (GPLv3+)
Classifier: Operating System :: OS Independent
Requires-Dist: sphinx
Requires-Dist: sphinx_rtd_theme
Requires-Dist: sphinx-autobuild
Requires-Dist: pygments
Requires-Dist: sphinx-tabs
Requires-Dist: sphinx-copybutton
Requires-Dist: sphinx-notfound-page
Requires-Dist: sphinxext-opengraph
Requires-Dist: sphinxcontrib-video
Requires-Dist: black ; extra == "dev"
Requires-Dist: flake8 ; extra == "dev"
Requires-Dist: flit ; extra == "dev"
Requires-Dist: build ; extra == "dev"
Requires-Dist: twine ; extra == "dev"
Project-URL: Homepage, https://gitlab.com/opsocket/sphinx_godot.git
Project-URL: Issues, https://gitlab.com/opsocket/sphinx_godot/-/issues
Provides-Extra: dev
